Workbook

Sheet Dashboard
B1: AXUDAR GROUP™ – WEBSITE QA PROGRESS DASHBOARD
B2: Build: https://auxder.vercel.app/ • Source: QA & Developer Action List, 03 October 2026
B4: Total Items | C4: Dev Complete % | D4: QA Passed % | E4: Client Approved % | F4: Fully Closed %
B5: =COUNTA('Action Tracker'!$A$5:$A$33) -> 29 | C5: =IFERROR(COUNTIF('Action Tracker'!$J$5:$J$33,"Done – Ready for QA")/B5,0) -> 0 | D5: =IFERROR(COUNTIF('Action Tracker'!$M$5:$M$33,"Pass")/B5,0) -> 0 | E5: =IFERROR(COUNTIF('Action Tracker'!$P$5:$P$33,"Approved")/B5,0) -> 0 | F5: =IFERROR(COUNTIF('Action Tracker'!$R$5:$R$33,"CLOSED")/B5,0) -> 0
B7: READY TO RETURN FOR QA? | C7: =IF(AND(COUNTIFS('Action Tracker'!$B$5:$B$33,"CRITICAL",'Action Tracker'!$J$5:$J$33,"<>Done – Ready for QA")=0,COUNTIFS('Action Tracker'!$B$5:$B$33,"HIGH",'Action Tracker'!$J$5:$J$33,"<>Done – Ready for QA")=0),"YES – all C & H items done","NO – "&(COUNTIFS('Action Tracker'!$B$5:$B$33,"CRITICAL",'Action Tracker'!$J$5:$J$33,"<>Done – Ready for QA")+COUNTIFS('Action Tracker'!$B$5:$B$33,"HIGH",'Action Tracker'!$J$5:$J$33,"<>Done – Ready for QA"))&" critical/high item(s) still open") -> NO – 21 critical/high item(s) still open
B9: By Priority – Developer Status
B10: Priority | C10: Total | D10: Open | E10: In Progress | F10: Done – Ready for QA | G10: Blocked | H10: % Dev Done
B11: CRITICAL | C11: =COUNTIF('Action Tracker'!$B$5:$B$33,B11) -> 5 | D11: =COUNTIFS('Action Tracker'!$B$5:$B$33,$B11,'Action Tracker'!$J$5:$J$33,"Open") -> 5 | E11: =COUNTIFS('Action Tracker'!$B$5:$B$33,$B11,'Action Tracker'!$J$5:$J$33,"In Progress") -> 0 | F11: =COUNTIFS('Action Tracker'!$B$5:$B$33,$B11,'Action Tracker'!$J$5:$J$33,"Done – Ready for QA") -> 0 | G11: =COUNTIFS('Action Tracker'!$B$5:$B$33,$B11,'Action Tracker'!$J$5:$J$33,"Blocked / Cannot Complete") -> 0 | H11: =IFERROR(F11/C11,0) -> 0
B12: HIGH | C12: =COUNTIF('Action Tracker'!$B$5:$B$33,B12) -> 16 | D12: =COUNTIFS('Action Tracker'!$B$5:$B$33,$B12,'Action Tracker'!$J$5:$J$33,"Open") -> 16 | E12: =COUNTIFS('Action Tracker'!$B$5:$B$33,$B12,'Action Tracker'!$J$5:$J$33,"In Progress") -> 0 | F12: =COUNTIFS('Action Tracker'!$B$5:$B$33,$B12,'Action Tracker'!$J$5:$J$33,"Done – Ready for QA") -> 0 | G12: =COUNTIFS('Action Tracker'!$B$5:$B$33,$B12,'Action Tracker'!$J$5:$J$33,"Blocked / Cannot Complete") -> 0 | H12: =IFERROR(F12/C12,0) -> 0
B13: MEDIUM | C13: =COUNTIF('Action Tracker'!$B$5:$B$33,B13) -> 8 | D13: =COUNTIFS('Action Tracker'!$B$5:$B$33,$B13,'Action Tracker'!$J$5:$J$33,"Open") -> 8 | E13: =COUNTIFS('Action Tracker'!$B$5:$B$33,$B13,'Action Tracker'!$J$5:$J$33,"In Progress") -> 0 | F13: =COUNTIFS('Action Tracker'!$B$5:$B$33,$B13,'Action Tracker'!$J$5:$J$33,"Done – Ready for QA") -> 0 | G13: =COUNTIFS('Action Tracker'!$B$5:$B$33,$B13,'Action Tracker'!$J$5:$J$33,"Blocked / Cannot Complete") -> 0 | H13: =IFERROR(F13/C13,0) -> 0
B14: TOTAL | C14: =SUM(C11:C13) -> 29 | D14: =SUM(D11:D13) -> 29 | E14: =SUM(E11:E13) -> 0 | F14: =SUM(F11:F13) -> 0 | G14: =SUM(G11:G13) -> 0 | H14: =IFERROR(F14/C14,0) -> 0
B16: Overall Status Breakdown | F16: QA & Client Snapshot
B17: Status | C17: Items | D17: % of Total | F17: Measure | H17: Items
B18: OPEN | C18: =COUNTIF('Action Tracker'!$R$5:$R$33,B18) -> 29 | D18: =IFERROR(C18/$B$5,0) -> 1 | F18: QA Not Tested | H18: =COUNTIF('Action Tracker'!$M$5:$M$33,"Not Tested") -> 29
B19: IN PROGRESS | C19: =COUNTIF('Action Tracker'!$R$5:$R$33,B19) -> 0 | D19: =IFERROR(C19/$B$5,0) -> 0 | F19: QA Pass | H19: =COUNTIF('Action Tracker'!$M$5:$M$33,"Pass") -> 0
B20: AWAITING QA | C20: =COUNTIF('Action Tracker'!$R$5:$R$33,B20) -> 0 | D20: =IFERROR(C20/$B$5,0) -> 0 | F20: QA Fail – Reopen | H20: =COUNTIF('Action Tracker'!$M$5:$M$33,"Fail – Reopen") -> 0
B21: REOPENED | C21: =COUNTIF('Action Tracker'!$R$5:$R$33,B21) -> 0 | D21: =IFERROR(C21/$B$5,0) -> 0 | F21: QA Retest Needed | H21: =COUNTIF('Action Tracker'!$M$5:$M$33,"Retest Needed") -> 0
B22: AWAITING CLIENT | C22: =COUNTIF('Action Tracker'!$R$5:$R$33,B22) -> 0 | D22: =IFERROR(C22/$B$5,0) -> 0 | F22: Client Pending | H22: =COUNTIF('Action Tracker'!$P$5:$P$33,"Pending") -> 29
B23: BLOCKED | C23: =COUNTIF('Action Tracker'!$R$5:$R$33,B23) -> 0 | D23: =IFERROR(C23/$B$5,0) -> 0 | F23: Client Approved | H23: =COUNTIF('Action Tracker'!$P$5:$P$33,"Approved") -> 0
B24: CLOSED | C24: =COUNTIF('Action Tracker'!$R$5:$R$33,B24) -> 0 | D24: =IFERROR(C24/$B$5,0) -> 0 | F24: Client Changes Req. | H24: =COUNTIF('Action Tracker'!$P$5:$P$33,"Changes Requested") -> 0
B25: TOTAL | C25: =SUM(C18:C24) -> 29 | D25: =SUM(D18:D24) -> 1
B27: Regression (passed items) still passing: | E27: =COUNTIF('Regression (Passed)'!D4:D9,"Still Passing")&" / "&COUNTA('Regression (Passed)'!A4:A9) -> 0 / 6
B28: Return-for-QA checklist complete: | E28: ='Return-for-QA Checklist'!C18 -> 0

Sheet Action Tracker
A1: AXUDAR GROUP™ – Website QA Action Tracker (build: https://auxder.vercel.app/ • list dated 03 Oct 2026)
A2: Edit the shaded input columns (G–I, J–L, M–O, P–Q). Column R is automatic.
A4: ID | B4: Priority | C4: Area | D4: Issue | E4: Current Problem | F4: Required Fix | G4: Tested Desktop? | H4: Tested Mobile? | I4: Developer | J4: Dev Status | K4: Dev Date Completed | L4: Dev Notes / Test Evidence (URL/screenshot) | M4: QA Status | N4: QA Date | O4: QA Feedback | P4: Client Review | Q4: Client Comments | R4: Overall Status
A5: C1 | B5: CRITICAL | C5: Enquiry flow | D5: SEO enquiry carries the wrong package | E5: Selecting SEO & AI Visibility at FROM £649 + VAT opens an enquiry showing Social Media Growth £399. | F5: SEO must carry SEO & AI Visibility and £649 through every enquiry step. Test homepage → package → enquiry and SEO detail page → enquiry. | G5: No | H5: No | J5: Open | M5: Not Tested | P5: Pending | R5: =IF(AND(J5="Done – Ready for QA",M5="Pass",P5="Approved"),"CLOSED",IF(J5="Blocked / Cannot Complete","BLOCKED",IF(M5="Fail – Reopen","REOPENED",IF(AND(J5="Done – Ready for QA",M5<>"Pass"),"AWAITING QA",IF(AND(M5="Pass",P5<>"Approved"),"AWAITING CLIENT",IF(J5="In Progress","IN PROGRESS","OPEN")))))) -> OPEN
A6: C2 | B6: CRITICAL | C6: Navigation / CTA | D6: Main “BUILD YOUR GROWTH CANVAS” CTA is wrong | E6: The header CTA routes to Contact instead of starting/opening the Growth Canvas. | F6: Route this CTA directly to the Growth Canvas journey. It must not behave like Contact. | G6: No | H6: No | J6: Open | M6: Not Tested | P6: Pending | R6: =IF(AND(J6="Done – Ready for QA",M6="Pass",P6="Approved"),"CLOSED",IF(J6="Blocked / Cannot Complete","BLOCKED",IF(M6="Fail – Reopen","REOPENED",IF(AND(J6="Done – Ready for QA",M6<>"Pass"),"AWAITING QA",IF(AND(M6="Pass",P6<>"Approved"),"AWAITING CLIENT",IF(J6="In Progress","IN PROGRESS","OPEN")))))) -> OPEN
A7: C3 | B7: CRITICAL | C7: Content | D7: Service pages contain copied Business Growth content | E7: Strategy, Marketing, SEO, Social Media and Website & Conversion are still using Business Growth copy/deliverables. | F7: Replace each page with its own approved service-specific hero copy, outcomes, deliverables and CTAs. No duplicated Business Growth content. | G7: No | H7: No | J7: Open | M7: Not Tested | P7: Pending | R7: =IF(AND(J7="Done – Ready for QA",M7="Pass",P7="Approved"),"CLOSED",IF(J7="Blocked / Cannot Complete","BLOCKED",IF(M7="Fail – Reopen","REOPENED",IF(AND(J7="Done – Ready for QA",M7<>"Pass"),"AWAITING QA",IF(AND(M7="Pass",P7<>"Approved"),"AWAITING CLIENT",IF(J7="In Progress","IN PROGRESS","OPEN")))))) -> OPEN
A8: C4 | B8: CRITICAL | C8: Site architecture | D8: Core journeys are not separate as requested | E8: Ecosystem, Growth Canvas and How It Works still resolve into / depend on homepage sections instead of clear standalone journeys. | F8: Create the agreed distinct routes/pages and ensure top navigation opens the correct page/route for each. | G8: No | H8: No | J8: Open | M8: Not Tested | P8: Pending | R8: =IF(AND(J8="Done – Ready for QA",M8="Pass",P8="Approved"),"CLOSED",IF(J8="Blocked / Cannot Complete","BLOCKED",IF(M8="Fail – Reopen","REOPENED",IF(AND(J8="Done – Ready for QA",M8<>"Pass"),"AWAITING QA",IF(AND(M8="Pass",P8<>"Approved"),"AWAITING CLIENT",IF(J8="In Progress","IN PROGRESS","OPEN")))))) -> OPEN
A9: C5 | B9: CRITICAL | C9: Enquiry flow | D9: Canvas → enquiry handoff is not fully reliable/clear | E9: The Canvas can hold selections, but the journey into enquiry is not clearly carrying and displaying all chosen areas/outcomes. | F9: When “Discuss My Canvas” is used, show the selected Canvas areas/outcomes clearly on the enquiry screen and include them in the submitted enquiry. | G9: No | H9: No | J9: Open | M9: Not Tested | P9: Pending | R9: =IF(AND(J9="Done – Ready for QA",M9="Pass",P9="Approved"),"CLOSED",IF(J9="Blocked / Cannot Complete","BLOCKED",IF(M9="Fail – Reopen","REOPENED",IF(AND(J9="Done – Ready for QA",M9<>"Pass"),"AWAITING QA",IF(AND(M9="Pass",P9<>"Approved"),"AWAITING CLIENT",IF(J9="In Progress","IN PROGRESS","OPEN")))))) -> OPEN
A10: H1 | B10: HIGH | C10: Contact form | D10: Contact form categories do not match the six Growth Areas | E10: Contact uses Strategy & Planning / Commercial Growth / SEO & AI Visibility / Social & Content / Website & Conversion / Campaigns & Leads. | F10: Use exactly: Business Growth; Strategy; Marketing; SEO & AI Visibility; Social Media; Website & Conversion. | G10: No | H10: No | J10: Open | M10: Not Tested | P10: Pending | R10: =IF(AND(J10="Done – Ready for QA",M10="Pass",P10="Approved"),"CLOSED",IF(J10="Blocked / Cannot Complete","BLOCKED",IF(M10="Fail – Reopen","REOPENED",IF(AND(J10="Done – Ready for QA",M10<>"Pass"),"AWAITING QA",IF(AND(M10="Pass",P10<>"Approved"),"AWAITING CLIENT",IF(J10="In Progress","IN PROGRESS","OPEN")))))) -> OPEN
A11: H2 | B11: HIGH | C11: Terminology | D11: “Strategy & Planning” still appears | E11: Legacy wording remains across pages, Canvas and footer. | F11: Replace all customer-facing “Strategy & Planning” references with “Strategy”. | G11: No | H11: No | J11: Open | M11: Not Tested | P11: Pending | R11: =IF(AND(J11="Done – Ready for QA",M11="Pass",P11="Approved"),"CLOSED",IF(J11="Blocked / Cannot Complete","BLOCKED",IF(M11="Fail – Reopen","REOPENED",IF(AND(J11="Done – Ready for QA",M11<>"Pass"),"AWAITING QA",IF(AND(M11="Pass",P11<>"Approved"),"AWAITING CLIENT",IF(J11="In Progress","IN PROGRESS","OPEN")))))) -> OPEN
A12: H3 | B12: HIGH | C12: Terminology | D12: “Connected Growth Solutions” wording is wrong | E12: Homepage still uses “6 Connected Growth Solutions”. | F12: Change to “6 Connected Growth Areas”. | G12: No | H12: No | J12: Open | M12: Not Tested | P12: Pending | R12: =IF(AND(J12="Done – Ready for QA",M12="Pass",P12="Approved"),"CLOSED",IF(J12="Blocked / Cannot Complete","BLOCKED",IF(M12="Fail – Reopen","REOPENED",IF(AND(J12="Done – Ready for QA",M12<>"Pass"),"AWAITING QA",IF(AND(M12="Pass",P12<>"Approved"),"AWAITING CLIENT",IF(J12="In Progress","IN PROGRESS","OPEN")))))) -> OPEN
A13: H4 | B13: HIGH | C13: Terminology | D13: Growth Engine wording remains | E13: Legacy “Growth Engine” wording is still visible. | F13: Remove legacy Growth Engine wording and use the new Growth Ecosystem / Growth Canvas terminology only. | G13: No | H13: No | J13: Open | M13: Not Tested | P13: Pending | R13: =IF(AND(J13="Done – Ready for QA",M13="Pass",P13="Approved"),"CLOSED",IF(J13="Blocked / Cannot Complete","BLOCKED",IF(M13="Fail – Reopen","REOPENED",IF(AND(J13="Done – Ready for QA",M13<>"Pass"),"AWAITING QA",IF(AND(M13="Pass",P13<>"Approved"),"AWAITING CLIENT",IF(J13="In Progress","IN PROGRESS","OPEN")))))) -> OPEN
A14: H5 | B14: HIGH | C14: Terminology | D14: 12-month wording remains | E14: “12 Month Partnership Model” and 12-month minimum wording are still visible. | F14: Remove the legacy 12-month partnership/minimum wording where previously requested. | G14: No | H14: No | J14: Open | M14: Not Tested | P14: Pending | R14: =IF(AND(J14="Done – Ready for QA",M14="Pass",P14="Approved"),"CLOSED",IF(J14="Blocked / Cannot Complete","BLOCKED",IF(M14="Fail – Reopen","REOPENED",IF(AND(J14="Done – Ready for QA",M14<>"Pass"),"AWAITING QA",IF(AND(M14="Pass",P14<>"Approved"),"AWAITING CLIENT",IF(J14="In Progress","IN PROGRESS","OPEN")))))) -> OPEN
A15: H6 | B15: HIGH | C15: Content | D15: SEO package detail page is incomplete/wrong | E15: The SEO detail page contains Business Growth/sales/pricing copy instead of full SEO content. | F15: Build the SEO page with the approved SEO & AI Visibility package content, deliverables and FROM £649 + VAT pricing. | G15: No | H15: No | J15: Open | M15: Not Tested | P15: Pending | R15: =IF(AND(J15="Done – Ready for QA",M15="Pass",P15="Approved"),"CLOSED",IF(J15="Blocked / Cannot Complete","BLOCKED",IF(M15="Fail – Reopen","REOPENED",IF(AND(J15="Done – Ready for QA",M15<>"Pass"),"AWAITING QA",IF(AND(M15="Pass",P15<>"Approved"),"AWAITING CLIENT",IF(J15="In Progress","IN PROGRESS","OPEN")))))) -> OPEN
A16: H7 | B16: HIGH | C16: Enquiry flow | D16: “Ask a question” loses package context | E16: A package can be passed in the URL but the visible form does not clearly show the customer what package they are asking about. | F16: Display the selected package name clearly on the form and include it in the submitted enquiry. | G16: No | H16: No | J16: Open | M16: Not Tested | P16: Pending | R16: =IF(AND(J16="Done – Ready for QA",M16="Pass",P16="Approved"),"CLOSED",IF(J16="Blocked / Cannot Complete","BLOCKED",IF(M16="Fail – Reopen","REOPENED",IF(AND(J16="Done – Ready for QA",M16<>"Pass"),"AWAITING QA",IF(AND(M16="Pass",P16<>"Approved"),"AWAITING CLIENT",IF(J16="In Progress","IN PROGRESS","OPEN")))))) -> OPEN
... A33: M8 | B33: MEDIUM | C33: Site architecture | D33: Legacy route naming remains | E33: Package URLs still expose /readyMadePackageDetails/. | F33: Rename/redirect legacy “Ready Made” routes where feasible so the public architecture matches the new proposition. | G33: No | H33: No | J33: Open | M33: Not Tested | P33: Pending | R33: =IF(AND(J33="Done – Ready for QA",M33="Pass",P33="Approved"),"CLOSED",IF(J33="Blocked / Cannot Complete","BLOCKED",IF(M33="Fail – Reopen","REOPENED",IF(AND(J33="Done – Ready for QA",M33<>"Pass"),"AWAITING QA",IF(AND(M33="Pass",P33<>"Approved"),"AWAITING CLIENT",IF(J33="In Progress","IN PROGRESS","OPEN")))))) -> OPEN

Sheet Regression (Passed)
A1: Passed / Improved Items – re-verify after fixes (do not regress)
A3: ID | B3: Item | C3: Status in 03 Oct QA | D3: Regression Result | E3: Checked By | F3: Date Checked | G3: Notes
A4: P1 | B4: Six “Choose Where You Need Support” cards link to service areas | C4: PASS / IMPROVED | D4: Not Rechecked
A5: P2 | B5: Six “+ Add to My Growth Canvas” links now pre-load Canvas areas | C5: PASS / IMPROVED | D5: Not Rechecked
A6: P3 | B6: Headline Social Media price shows FROM £399 + VAT | C6: PASS | D6: Not Rechecked
A7: P4 | B7: Headline SEO & AI Visibility price shows FROM £649 + VAT | C7: PASS | D7: Not Rechecked
A8: P5 | B8: Insights landing page and checked articles open | C8: PASS | D8: Not Rechecked
A9: P6 | B9: Main phone number displays as 0330 133 5720 | C9: PASS | D9: Not Rechecked

Sheet Return-for-QA Checklist
A1: Return-for-QA Checklist – complete every line before re-submitting
A3: # | B3: Checklist Item | C3: Status | D3: Completed By | E3: Date | F3: Notes
A4: 1 | B4: All C1–C5 critical items completed and tested. | C4: Not Started
A5: 2 | B5: All H1–H16 high-priority items completed. | C5: Not Started
A6: 3 | B6: Every top-navigation link checked on desktop and mobile. | C6: Not Started
A7: 4 | B7: Every clickable service card/box checked on desktop and mobile. | C7: Not Started
A8: 5 | B8: Every “Add to My Growth Canvas” action checked. | C8: Not Started
A9: 6 | B9: Every package CTA checked through to the final enquiry screen. | C9: Not Started
A10: 7 | B10: All form fields, validation, submit action and confirmation state tested. | C10: Not Started
A11: 8 | B11: Correct package/service name and price retained throughout the journey. | C11: Not Started
A12: 9 | B12: No old terminology remains: Strategy & Planning / Growth Engine / Ready Made / 12 Month Partnership Model. | C12: Not Started
A13: 10 | B13: No placeholder, duplicated or unrelated content remains. | C13: Not Started
A14: 11 | B14: Footer, contact details and legal links checked on every template. | C14: Not Started
A15: 12 | B15: Page titles/meta checked for homepage, six services, packages, Results, Insights articles and Contact. | C15: Not Started
A16: 13 | B16: Final mobile check completed at common phone widths before resubmission. | C16: Not Started
B18: Checklist completion | C18: =IFERROR(COUNTIF(C4:C16,"Complete")/(COUNTA(C4:C16)-COUNTIF(C4:C16,"N/A")),0) -> 0

Sheet Legend & Lists
A1: Developer Status | B1: QA Status | C1: Client Review | D1: Checklist Status | E1: Regression Result | F1: Priority
A2: Open | B2: Not Tested | C2: Pending | D2: Not Started | E2: Not Rechecked | F2: CRITICAL
A3: In Progress | B3: Pass | C3: Approved | D3: In Progress | E3: Still Passing | F3: HIGH
A4: Done – Ready for QA | B4: Fail – Reopen | C4: Changes Requested | D4: Complete | E4: Regressed | F4: MEDIUM
A5: Blocked / Cannot Complete | B5: Retest Needed | D5: N/A
A9: How to use
A10: • Developer sets Dev Status (and Date Completed) after testing on desktop AND mobile.
A11: • QA sets QA Status after independent retest. Fail – Reopen puts the item back to work.
A12: • Client sets Client Review once QA has passed. Yellow-bordered columns are the ones to edit.
A13: • An item is fully CLOSED only when Dev = Done, QA = Pass and Client = Approved.
A14: • Dashboard and Checklist totals recalculate automatically from the tracker.
